s3py/__init__.py
s3py/error.py
s3py/group.py
s3py/name.py
s3py/param.py
s3py/param_db.py
s3py/path.py
s3py/s3_pprint.py
s3py/sys.py
s3py/io/__init__.py
s3py/io/base_node.py
s3py/io/node.py
s3py/io/protocol_message.py
s3py/io/requests.py
s3py-0.0.1.dist-info/METADATA
s3py-0.0.1.dist-info/WHEEL
s3py-0.0.1.dist-info/licenses/LICENSE
s3py-0.0.1.dist-info/RECORD
